AUTHORS
CHANGELOG.rst
LICENSE
MANIFEST.in
README.rst
setup.py
django_queue_mailer/__init__.py
django_queue_mailer/admin.py
django_queue_mailer/backend.py
django_queue_mailer/defaults.py
django_queue_mailer/models.py
django_queue_mailer/sentry.py
django_queue_mailer.egg-info/PKG-INFO
django_queue_mailer.egg-info/SOURCES.txt
django_queue_mailer.egg-info/dependency_links.txt
django_queue_mailer.egg-info/top_level.txt
django_queue_mailer/locale/sk/LC_MESSAGES/django.mo
django_queue_mailer/locale/sk/LC_MESSAGES/django.po
django_queue_mailer/management/__init__.py
django_queue_mailer/management/commands/__init__.py
django_queue_mailer/management/commands/clear_sent_messages.py
django_queue_mailer/management/commands/migrate_django_mailer.py
django_queue_mailer/management/commands/send_queued_messages.py
django_queue_mailer/management/commands/test_mail.py
django_queue_mailer/migrations/0001_initial.py
django_queue_mailer/migrations/0002_auto_20191031_1345.py
django_queue_mailer/migrations/__init__.py